{
    "layers": [
        {
            "advanceWidth": 1200, 
            "color": "#b9baa2", 
            "elements": [
                {
                    "elementData": {
                        "contours": [
                            {
                                "nodes": [
                                    "400 1520", 
                                    "800 1520", 
                                    "800 -480", 
                                    "400 -480"
                                ]
                            }
                        ]
                    }
                }
            ], 
            "flags": 0, 
            "metricsLeft": "=H", 
            "metricsRight": "=H", 
            "name": "Blk Exp Ctr"
        }, 
        {
            "advanceWidth": 1030, 
            "color": "#809693", 
            "elements": [
                {
                    "elementData": {
                        "contours": [
                            {
                                "nodes": [
                                    "400 1520", 
                                    "630 1520", 
                                    "630 -480", 
                                    "400 -480"
                                ]
                            }
                        ]
                    }
                }
            ], 
            "flags": 0, 
            "metricsLeft": "=H", 
            "metricsRight": "=H", 
            "name": "Exp Ctr"
        }, 
        {
            "advanceWidth": 740, 
            "color": "#c8675e", 
            "elements": [
                {
                    "elementData": {
                        "contours": [
                            {
                                "nodes": [
                                    "350 1520", 
                                    "390 1520", 
                                    "390 -480", 
                                    "350 -480"
                                ]
                            }
                        ]
                    }
                }
            ], 
            "flags": 0, 
            "metricsLeft": "=H", 
            "metricsRight": "=H", 
            "name": "Lt Exp Ctr"
        }, 
        {
            "advanceWidth": 576, 
            "color": "#997d87", 
            "elements": [
                {
                    "elementData": {
                        "contours": [
                            {
                                "nodes": [
                                    "88 1520", 
                                    "488 1520", 
                                    "488 -480", 
                                    "88 -480"
                                ]
                            }
                        ]
                    }
                }
            ], 
            "flags": 0, 
            "metricsLeft": "=H", 
            "metricsRight": "=H", 
            "name": "Blk Cnd Ctr"
        }, 
        {
            "advanceWidth": 442, 
            "color": "#8fb0ff", 
            "elements": [
                {
                    "elementData": {
                        "contours": [
                            {
                                "nodes": [
                                    "106 1520", 
                                    "336 1520", 
                                    "336 -480", 
                                    "106 -480"
                                ]
                            }
                        ]
                    }
                }
            ], 
            "flags": 0, 
            "metricsLeft": "=H", 
            "metricsRight": "=H", 
            "name": "Cnd Ctr"
        }, 
        {
            "advanceWidth": 230, 
            "color": "#4e8e82", 
            "elements": [
                {
                    "elementData": {
                        "contours": [
                            {
                                "nodes": [
                                    "95 1520", 
                                    "135 1520", 
                                    "135 -480", 
                                    "95 -480"
                                ]
                            }
                        ]
                    }
                }
            ], 
            "flags": 0, 
            "metricsLeft": "=H", 
            "metricsRight": "=H", 
            "name": "Lt Cnd Ctr"
        }, 
        {
            "advanceWidth": 800, 
            "color": "#b69762", 
            "elements": [
                {
                    "elementData": {
                        "contours": [
                            {
                                "nodes": [
                                    "200 1520", 
                                    "600 1520", 
                                    "600 -480", 
                                    "200 -480"
                                ]
                            }
                        ]
                    }
                }
            ], 
            "flags": 0, 
            "metricsLeft": "=H", 
            "metricsRight": "=H", 
            "name": "Blk Ctr"
        }, 
        {
            "advanceWidth": 670, 
            "color": "#26d283", 
            "elements": [
                {
                    "elementData": {
                        "contours": [
                            {
                                "nodes": [
                                    "220 1520", 
                                    "450 1520", 
                                    "450 -480", 
                                    "220 -480"
                                ]
                            }
                        ]
                    }
                }
            ], 
            "flags": 0, 
            "metricsLeft": "=H", 
            "metricsRight": "=H", 
            "name": "Ctr"
        }, 
        {
            "advanceWidth": 610, 
            "color": "#9061ff", 
            "elements": [
                {
                    "elementData": {
                        "contours": [
                            {
                                "nodes": [
                                    "285 1520", 
                                    "325 1520", 
                                    "325 -480", 
                                    "285 -480"
                                ]
                            }
                        ]
                    }
                }
            ], 
            "flags": 0, 
            "metricsLeft": "=H", 
            "metricsRight": "=H", 
            "name": "Lt Ctr"
        }, 
        {
            "advanceWidth": 1040, 
            "color": "#b07733", 
            "elements": [
                {
                    "elementData": {
                        "contours": [
                            {
                                "nodes": [
                                    "320 1520", 
                                    "720 1520", 
                                    "720 -480", 
                                    "320 -480"
                                ]
                            }
                        ]
                    }
                }
            ], 
            "flags": 0, 
            "metricsLeft": "=H", 
            "metricsRight": "=H", 
            "name": "Blk Exp"
        }, 
        {
            "advanceWidth": 850, 
            "color": "#d2afb9", 
            "elements": [
                {
                    "elementData": {
                        "contours": [
                            {
                                "nodes": [
                                    "310 1520", 
                                    "540 1520", 
                                    "540 -480", 
                                    "310 -480"
                                ]
                            }
                        ]
                    }
                }
            ], 
            "flags": 0, 
            "metricsLeft": "=H", 
            "metricsRight": "=H", 
            "name": "Exp"
        }, 
        {
            "advanceWidth": 740, 
            "color": "#de4d8a", 
            "elements": [
                {
                    "elementData": {
                        "contours": [
                            {
                                "nodes": [
                                    "350 1520", 
                                    "390 1520", 
                                    "390 -480", 
                                    "350 -480"
                                ]
                            }
                        ]
                    }
                }
            ], 
            "flags": 0, 
            "metricsLeft": "=H", 
            "metricsRight": "=H", 
            "name": "Lt Exp"
        }, 
        {
            "advanceWidth": 560, 
            "color": "#3989c2", 
            "elements": [
                {
                    "elementData": {
                        "contours": [
                            {
                                "nodes": [
                                    "80 1520", 
                                    "480 1520", 
                                    "480 -480", 
                                    "80 -480"
                                ]
                            }
                        ]
                    }
                }
            ], 
            "flags": 0, 
            "metricsLeft": "=H", 
            "metricsRight": "=H", 
            "name": "Blk Cnd"
        }, 
        {
            "advanceWidth": 374, 
            "color": "#1f964d", 
            "elements": [
                {
                    "elementData": {
                        "contours": [
                            {
                                "nodes": [
                                    "72 1520", 
                                    "302 1520", 
                                    "302 -480", 
                                    "72 -480"
                                ]
                            }
                        ]
                    }
                }
            ], 
            "flags": 0, 
            "metricsLeft": "=H", 
            "metricsRight": "=H", 
            "name": "Cnd"
        }, 
        {
            "advanceWidth": 230, 
            "color": "#fe4a46", 
            "elements": [
                {
                    "elementData": {
                        "contours": [
                            {
                                "nodes": [
                                    "95 1520", 
                                    "135 1520", 
                                    "135 -480", 
                                    "95 -480"
                                ]
                            }
                        ]
                    }
                }
            ], 
            "flags": 0, 
            "metricsLeft": "=H", 
            "metricsRight": "=H", 
            "name": "Lt Cnd"
        }, 
        {
            "advanceWidth": 760, 
            "color": "#ff34ff", 
            "elements": [
                {
                    "elementData": {
                        "contours": [
                            {
                                "nodes": [
                                    "180 1520", 
                                    "580 1520", 
                                    "580 -480", 
                                    "180 -480"
                                ]
                            }
                        ]
                    }
                }
            ], 
            "flags": 0, 
            "metricsLeft": "=H", 
            "metricsRight": "=H", 
            "name": "Blk"
        }, 
        {
            "advanceWidth": 630, 
            "color": "#00cce5", 
            "elements": [
                {
                    "elementData": {
                        "contours": [
                            {
                                "nodes": [
                                    "200 1520", 
                                    "430 1520", 
                                    "430 -480", 
                                    "200 -480"
                                ]
                            }
                        ]
                    }
                }
            ], 
            "flags": 0, 
            "metricsLeft": "=H", 
            "metricsRight": "=H", 
            "name": "Medium"
        }, 
        {
            "advanceWidth": 610, 
            "color": "#bac000", 
            "elements": [
                {
                    "elementData": {
                        "contours": [
                            {
                                "nodes": [
                                    "285 1520", 
                                    "325 1520", 
                                    "325 -480", 
                                    "285 -480"
                                ]
                            }
                        ]
                    }
                }
            ], 
            "flags": 0, 
            "metricsLeft": "=H", 
            "metricsRight": "=H", 
            "name": "Lt"
        }
    ], 
    "name": "bar", 
    "tags": [
        "T"
    ], 
    "unicode": "007c"
}