{
    "lastModified": "2019-10-14 06:59:24", 
    "layers": [
        {
            "advanceWidth": 1285, 
            "autoRecipe": "=braceleft@~,~", 
            "color": "#b9baa2", 
            "elements": [
                {
                    "active": true, 
                    "elementData": {
                        "component": {
                            "glyphName": "braceleft"
                        }, 
                        "name": "braceright"
                    }, 
                    "locked": true, 
                    "transform": {
                        "xOffset": 1261, 
                        "xScale": -1, 
                        "yOffset": 1192, 
                        "yScale": -1
                    }
                }
            ], 
            "flags": 0, 
            "metricsLeft": "=T", 
            "metricsRight": "=(T+t+H)/3", 
            "name": "Blk Exp Ctr"
        }, 
        {
            "advanceWidth": 1159, 
            "autoRecipe": "=braceleft@~,~", 
            "color": "#809693", 
            "elements": [
                {
                    "elementData": {
                        "component": {
                            "glyphName": "braceleft"
                        }, 
                        "name": "braceright"
                    }, 
                    "locked": true, 
                    "transform": {
                        "xOffset": 1166, 
                        "xScale": -1, 
                        "yOffset": 1192, 
                        "yScale": -1
                    }
                }
            ], 
            "flags": 0, 
            "metricsLeft": "=T", 
            "metricsRight": "=(T+t+H)/3", 
            "name": "Exp Ctr"
        }, 
        {
            "advanceWidth": 943, 
            "autoRecipe": "=braceleft@~,~", 
            "color": "#c8675e", 
            "elements": [
                {
                    "elementData": {
                        "component": {
                            "glyphName": "braceleft"
                        }, 
                        "name": "braceright"
                    }, 
                    "locked": true, 
                    "transform": {
                        "xOffset": 931, 
                        "xScale": -1, 
                        "yOffset": 1192, 
                        "yScale": -1
                    }
                }
            ], 
            "flags": 0, 
            "metricsLeft": "=T", 
            "metricsRight": "=(T+t+H)/3", 
            "name": "Lt Exp Ctr"
        }, 
        {
            "advanceWidth": 873, 
            "autoRecipe": "=braceleft@~,~", 
            "color": "#997d87", 
            "elements": [
                {
                    "elementData": {
                        "component": {
                            "glyphName": "braceleft"
                        }, 
                        "name": "braceright"
                    }, 
                    "locked": true, 
                    "transform": {
                        "xOffset": 874, 
                        "xScale": -1, 
                        "yOffset": 1192, 
                        "yScale": -1
                    }
                }
            ], 
            "flags": 0, 
            "metricsLeft": "=T", 
            "metricsRight": "=(T+t+H)/3", 
            "name": "Blk Cnd Ctr"
        }, 
        {
            "advanceWidth": 648, 
            "autoRecipe": "=braceleft@~,~", 
            "color": "#8fb0ff", 
            "elements": [
                {
                    "elementData": {
                        "component": {
                            "glyphName": "braceleft"
                        }, 
                        "name": "braceright"
                    }, 
                    "locked": true, 
                    "transform": {
                        "xOffset": 650, 
                        "xScale": -1, 
                        "yOffset": 1192, 
                        "yScale": -1
                    }
                }
            ], 
            "flags": 0, 
            "metricsLeft": "=T", 
            "metricsRight": "=(T+t+H)/3", 
            "name": "Cnd Ctr"
        }, 
        {
            "advanceWidth": 515, 
            "autoRecipe": "=braceleft@~,~", 
            "color": "#4e8e82", 
            "elements": [
                {
                    "elementData": {
                        "component": {
                            "glyphName": "braceleft"
                        }, 
                        "name": "braceright"
                    }, 
                    "locked": true, 
                    "transform": {
                        "xOffset": 518, 
                        "xScale": -1, 
                        "yOffset": 1192, 
                        "yScale": -1
                    }
                }
            ], 
            "flags": 0, 
            "metricsLeft": "=T", 
            "metricsRight": "=(T+t+H)/3", 
            "name": "Lt Cnd Ctr"
        }, 
        {
            "advanceWidth": 1033, 
            "autoRecipe": "=braceleft@~,~", 
            "color": "#b69762", 
            "elements": [
                {
                    "elementData": {
                        "component": {
                            "glyphName": "braceleft"
                        }, 
                        "name": "braceright"
                    }, 
                    "locked": true, 
                    "transform": {
                        "xOffset": 1029, 
                        "xScale": -1, 
                        "yOffset": 1192, 
                        "yScale": -1
                    }
                }
            ], 
            "flags": 0, 
            "metricsLeft": "=T", 
            "metricsRight": "=(T+t+H)/3", 
            "name": "Blk Ctr"
        }, 
        {
            "advanceWidth": 838, 
            "autoRecipe": "=braceleft@~,~", 
            "color": "#26d283", 
            "elements": [
                {
                    "elementData": {
                        "component": {
                            "glyphName": "braceleft"
                        }, 
                        "name": "braceright"
                    }, 
                    "locked": true, 
                    "transform": {
                        "xOffset": 829, 
                        "xScale": -1, 
                        "yOffset": 1192, 
                        "yScale": -1
                    }
                }
            ], 
            "flags": 0, 
            "metricsLeft": "=T", 
            "metricsRight": "=(T+t+H)/3", 
            "name": "Ctr"
        }, 
        {
            "advanceWidth": 776, 
            "autoRecipe": "=braceleft@~,~", 
            "color": "#9061ff", 
            "elements": [
                {
                    "elementData": {
                        "component": {
                            "glyphName": "braceleft"
                        }, 
                        "name": "braceright"
                    }, 
                    "locked": true, 
                    "transform": {
                        "xOffset": 798, 
                        "xScale": -1, 
                        "yOffset": 1192, 
                        "yScale": -1
                    }
                }
            ], 
            "flags": 0, 
            "metricsLeft": "=T", 
            "metricsRight": "=(T+t+H)/3", 
            "name": "Lt Ctr"
        }, 
        {
            "advanceWidth": 1322, 
            "autoRecipe": "=braceleft@~,~", 
            "color": "#b07733", 
            "elements": [
                {
                    "elementData": {
                        "component": {
                            "glyphName": "braceleft"
                        }, 
                        "name": "braceright"
                    }, 
                    "locked": true, 
                    "transform": {
                        "xOffset": 1312, 
                        "xScale": -1, 
                        "yOffset": 1192, 
                        "yScale": -1
                    }
                }
            ], 
            "flags": 0, 
            "metricsLeft": "=T", 
            "metricsRight": "=(T+t+H)/3", 
            "name": "Blk Exp"
        }, 
        {
            "advanceWidth": 1018, 
            "autoRecipe": "=braceleft@~,~", 
            "color": "#d2afb9", 
            "elements": [
                {
                    "elementData": {
                        "component": {
                            "glyphName": "braceleft"
                        }, 
                        "name": "braceright"
                    }, 
                    "locked": true, 
                    "transform": {
                        "xOffset": 990, 
                        "xScale": -1, 
                        "yOffset": 1192, 
                        "yScale": -1
                    }
                }
            ], 
            "flags": 0, 
            "metricsLeft": "=T", 
            "metricsRight": "=(T+t+H)/3", 
            "name": "Exp"
        }, 
        {
            "advanceWidth": 943, 
            "autoRecipe": "=braceleft@~,~", 
            "color": "#de4d8a", 
            "elements": [
                {
                    "elementData": {
                        "component": {
                            "glyphName": "braceleft"
                        }, 
                        "name": "braceright"
                    }, 
                    "locked": true, 
                    "transform": {
                        "xOffset": 931, 
                        "xScale": -1, 
                        "yOffset": 1192, 
                        "yScale": -1
                    }
                }
            ], 
            "flags": 0, 
            "metricsLeft": "=T", 
            "metricsRight": "=(T+t+H)/3", 
            "name": "Lt Exp"
        }, 
        {
            "advanceWidth": 887, 
            "autoRecipe": "=braceleft@~,~", 
            "color": "#3989c2", 
            "elements": [
                {
                    "elementData": {
                        "component": {
                            "glyphName": "braceleft"
                        }, 
                        "name": "braceright"
                    }, 
                    "locked": true, 
                    "transform": {
                        "xOffset": 887, 
                        "xScale": -1, 
                        "yOffset": 1192, 
                        "yScale": -1
                    }
                }
            ], 
            "flags": 0, 
            "metricsLeft": "=T", 
            "metricsRight": "=(T+t+H)/3", 
            "name": "Blk Cnd"
        }, 
        {
            "advanceWidth": 629, 
            "autoRecipe": "=braceleft@~,~", 
            "color": "#1f964d", 
            "elements": [
                {
                    "elementData": {
                        "component": {
                            "glyphName": "braceleft"
                        }, 
                        "name": "braceright"
                    }, 
                    "locked": true, 
                    "transform": {
                        "xOffset": 629, 
                        "xScale": -1, 
                        "yOffset": 1192, 
                        "yScale": -1
                    }
                }
            ], 
            "flags": 0, 
            "metricsLeft": "=T", 
            "metricsRight": "=(T+t+H)/3", 
            "name": "Cnd"
        }, 
        {
            "advanceWidth": 515, 
            "autoRecipe": "=braceleft@~,~", 
            "color": "#fe4a46", 
            "elements": [
                {
                    "elementData": {
                        "component": {
                            "glyphName": "braceleft"
                        }, 
                        "name": "braceright"
                    }, 
                    "locked": true, 
                    "transform": {
                        "xOffset": 518, 
                        "xScale": -1, 
                        "yOffset": 1192, 
                        "yScale": -1
                    }
                }
            ], 
            "flags": 0, 
            "metricsLeft": "=T", 
            "metricsRight": "=(T+t+H)/3", 
            "name": "Lt Cnd"
        }, 
        {
            "advanceWidth": 1101, 
            "autoRecipe": "=braceleft@~,~", 
            "color": "#ff34ff", 
            "elements": [
                {
                    "active": true, 
                    "elementData": {
                        "component": {
                            "glyphName": "braceleft"
                        }, 
                        "name": "braceright"
                    }, 
                    "locked": true, 
                    "transform": {
                        "xOffset": 1087, 
                        "xScale": -1, 
                        "yOffset": 1192, 
                        "yScale": -1
                    }
                }
            ], 
            "flags": 0, 
            "metricsLeft": "=T", 
            "metricsRight": "=(T+t+H)/3", 
            "name": "Blk"
        }, 
        {
            "advanceWidth": 833, 
            "autoRecipe": "=braceleft@~,~", 
            "color": "#00cce5", 
            "elements": [
                {
                    "active": true, 
                    "elementData": {
                        "component": {
                            "glyphName": "braceleft"
                        }, 
                        "name": "braceright"
                    }, 
                    "locked": true, 
                    "transform": {
                        "xOffset": 832, 
                        "xScale": -1, 
                        "yOffset": 1192, 
                        "yScale": -1
                    }
                }
            ], 
            "flags": 0, 
            "metricsLeft": "=T", 
            "metricsRight": "=(T+t+H)/3", 
            "name": "Medium"
        }, 
        {
            "active": true, 
            "advanceWidth": 787, 
            "autoRecipe": "=braceleft@~,~", 
            "color": "#bac000", 
            "elements": [
                {
                    "elementData": {
                        "component": {
                            "glyphName": "braceleft"
                        }, 
                        "name": "braceright"
                    }, 
                    "locked": true, 
                    "transform": {
                        "xOffset": 798, 
                        "xScale": -1, 
                        "yOffset": 1192, 
                        "yScale": -1
                    }
                }
            ], 
            "flags": 0, 
            "metricsLeft": "=T", 
            "metricsRight": "=(T+t+H)/3", 
            "name": "Lt"
        }
    ], 
    "name": "braceright", 
    "tags": [
        "T"
    ], 
    "unicode": "007d"
}