{
    "colorFlag": 241, 
    "lastModified": "2019-09-23 20:08:19", 
    "layers": [
        {
            "advanceWidth": 1748, 
            "color": "#b9baa2", 
            "colorFlag": 241, 
            "elements": [
                {
                    "active": true, 
                    "elementData": {
                        "contours": [
                            {
                                "nodes": [
                                    "206 740", 
                                    "1605 740", 
                                    "1615 776", 
                                    "206 776"
                                ]
                            }, 
                            {
                                "nodes": [
                                    "206 530", 
                                    "1605 530", 
                                    "1615 566", 
                                    "206 566"
                                ]
                            }
                        ]
                    }, 
                    "transform": {
                        "xOffset": -181
                    }
                }
            ], 
            "flags": 0, 
            "hints": [
                {
                    "position": 554, 
                    "thickness": 572, 
                    "vertical": true
                }, 
                {
                    "position": 2384, 
                    "thickness": 572, 
                    "vertical": true
                }, 
                {
                    "horizontal": true, 
                    "thickness": 484
                }, 
                {
                    "horizontal": true, 
                    "position": 916, 
                    "thickness": 484
                }, 
                {
                    "position": -1240, 
                    "thickness": 572, 
                    "vertical": true
                }, 
                {
                    "position": 590, 
                    "thickness": 572, 
                    "vertical": true
                }, 
                {
                    "horizontal": true, 
                    "thickness": 484
                }, 
                {
                    "horizontal": true, 
                    "position": 916, 
                    "thickness": 484
                }, 
                {
                    "position": 554, 
                    "thickness": 572, 
                    "vertical": true
                }, 
                {
                    "position": 2384, 
                    "thickness": 572, 
                    "vertical": true
                }, 
                {
                    "horizontal": true, 
                    "thickness": 484
                }, 
                {
                    "horizontal": true, 
                    "position": 916, 
                    "thickness": 484
                }, 
                {
                    "position": 554, 
                    "thickness": 572, 
                    "vertical": true
                }, 
                {
                    "position": 2384, 
                    "thickness": 572, 
                    "vertical": true
                }, 
                {
                    "horizontal": true, 
                    "position": 110, 
                    "thickness": 484
                }, 
                {
                    "horizontal": true, 
                    "position": 1026, 
                    "thickness": 484
                }, 
                {
                    "position": -1240, 
                    "thickness": 572, 
                    "vertical": true
                }, 
                {
                    "position": 590, 
                    "thickness": 572, 
                    "vertical": true
                }, 
                {
                    "horizontal": true, 
                    "position": 110, 
                    "thickness": 484
                }, 
                {
                    "horizontal": true, 
                    "position": 1026, 
                    "thickness": 484
                }, 
                {
                    "position": 554, 
                    "thickness": 572, 
                    "vertical": true
                }, 
                {
                    "position": 2384, 
                    "thickness": 572, 
                    "vertical": true
                }, 
                {
                    "horizontal": true, 
                    "position": 110, 
                    "thickness": 484
                }, 
                {
                    "horizontal": true, 
                    "position": 1026, 
                    "thickness": 484
                }, 
                {
                    "position": 554, 
                    "thickness": 572, 
                    "vertical": true
                }, 
                {
                    "position": 2384, 
                    "thickness": 572, 
                    "vertical": true
                }, 
                {
                    "horizontal": true, 
                    "position": -100, 
                    "thickness": 484
                }, 
                {
                    "horizontal": true, 
                    "position": 816, 
                    "thickness": 484
                }, 
                {
                    "position": -1240, 
                    "thickness": 572, 
                    "vertical": true
                }, 
                {
                    "position": 590, 
                    "thickness": 572, 
                    "vertical": true
                }, 
                {
                    "horizontal": true, 
                    "position": -100, 
                    "thickness": 484
                }, 
                {
                    "horizontal": true, 
                    "position": 816, 
                    "thickness": 484
                }, 
                {
                    "position": 554, 
                    "thickness": 572, 
                    "vertical": true
                }, 
                {
                    "position": 2384, 
                    "thickness": 572, 
                    "vertical": true
                }, 
                {
                    "horizontal": true, 
                    "position": -100, 
                    "thickness": 484
                }, 
                {
                    "horizontal": true, 
                    "position": 816, 
                    "thickness": 484
                }
            ], 
            "metricsLeft": "=T+15", 
            "metricsRight": "=C-10", 
            "name": "Blk Exp Ctr"
        }, 
        {
            "advanceWidth": 1632, 
            "color": "#809693", 
            "colorFlag": 241, 
            "elements": [
                {
                    "elementData": {
                        "contours": [
                            {
                                "nodes": [
                                    "196 740", 
                                    "1545 740", 
                                    "1555 776", 
                                    "196 776"
                                ]
                            }, 
                            {
                                "nodes": [
                                    "196 530", 
                                    "1545 530", 
                                    "1555 566", 
                                    "196 566"
                                ]
                            }
                        ]
                    }, 
                    "transform": {
                        "xOffset": -171
                    }
                }
            ], 
            "flags": 0, 
            "hints": [
                {
                    "position": 590, 
                    "thickness": 280, 
                    "vertical": true
                }, 
                {
                    "position": 2482, 
                    "thickness": 280, 
                    "vertical": true
                }, 
                {
                    "horizontal": true, 
                    "thickness": 40
                }, 
                {
                    "horizontal": true, 
                    "position": 1360, 
                    "thickness": 40
                }, 
                {
                    "position": -1330, 
                    "thickness": 280, 
                    "vertical": true
                }, 
                {
                    "position": 562, 
                    "thickness": 280, 
                    "vertical": true
                }, 
                {
                    "horizontal": true, 
                    "thickness": 40
                }, 
                {
                    "horizontal": true, 
                    "position": 1360, 
                    "thickness": 40
                }, 
                {
                    "position": 590, 
                    "thickness": 280, 
                    "vertical": true
                }, 
                {
                    "position": 2482, 
                    "thickness": 280, 
                    "vertical": true
                }, 
                {
                    "horizontal": true, 
                    "thickness": 40
                }, 
                {
                    "horizontal": true, 
                    "position": 1360, 
                    "thickness": 40
                }, 
                {
                    "position": 590, 
                    "thickness": 280, 
                    "vertical": true
                }, 
                {
                    "position": 2482, 
                    "thickness": 280, 
                    "vertical": true
                }, 
                {
                    "horizontal": true, 
                    "position": 110, 
                    "thickness": 40
                }, 
                {
                    "horizontal": true, 
                    "position": 1470, 
                    "thickness": 40
                }, 
                {
                    "position": -1330, 
                    "thickness": 280, 
                    "vertical": true
                }, 
                {
                    "position": 562, 
                    "thickness": 280, 
                    "vertical": true
                }, 
                {
                    "horizontal": true, 
                    "position": 110, 
                    "thickness": 40
                }, 
                {
                    "horizontal": true, 
                    "position": 1470, 
                    "thickness": 40
                }, 
                {
                    "position": 590, 
                    "thickness": 280, 
                    "vertical": true
                }, 
                {
                    "position": 2482, 
                    "thickness": 280, 
                    "vertical": true
                }, 
                {
                    "horizontal": true, 
                    "position": 110, 
                    "thickness": 40
                }, 
                {
                    "horizontal": true, 
                    "position": 1470, 
                    "thickness": 40
                }, 
                {
                    "position": 590, 
                    "thickness": 280, 
                    "vertical": true
                }, 
                {
                    "position": 2482, 
                    "thickness": 280, 
                    "vertical": true
                }, 
                {
                    "horizontal": true, 
                    "position": -100, 
                    "thickness": 40
                }, 
                {
                    "horizontal": true, 
                    "position": 1260, 
                    "thickness": 40
                }, 
                {
                    "position": -1330, 
                    "thickness": 280, 
                    "vertical": true
                }, 
                {
                    "position": 562, 
                    "thickness": 280, 
                    "vertical": true
                }, 
                {
                    "horizontal": true, 
                    "position": -100, 
                    "thickness": 40
                }, 
                {
                    "horizontal": true, 
                    "position": 1260, 
                    "thickness": 40
                }, 
                {
                    "position": 590, 
                    "thickness": 280, 
                    "vertical": true
                }, 
                {
                    "position": 2482, 
                    "thickness": 280, 
                    "vertical": true
                }, 
                {
                    "horizontal": true, 
                    "position": -100, 
                    "thickness": 40
                }, 
                {
                    "horizontal": true, 
                    "position": 1260, 
                    "thickness": 40
                }
            ], 
            "metricsLeft": "=T+15", 
            "metricsRight": "=C-10", 
            "name": "Exp Ctr"
        }, 
        {
            "advanceWidth": 1475, 
            "color": "#c8675e", 
            "colorFlag": 241, 
            "elements": [
                {
                    "elementData": {
                        "contours": [
                            {
                                "nodes": [
                                    "226 710", 
                                    "1345 710", 
                                    "1355 746", 
                                    "226 746"
                                ]
                            }, 
                            {
                                "nodes": [
                                    "226 500", 
                                    "1345 500", 
                                    "1355 536", 
                                    "226 536"
                                ]
                            }
                        ]
                    }, 
                    "transform": {
                        "xOffset": -206
                    }
                }
            ], 
            "flags": 0, 
            "hints": [
                {
                    "position": 544, 
                    "thickness": 40, 
                    "vertical": true
                }, 
                {
                    "position": 2372, 
                    "thickness": 40, 
                    "vertical": true
                }, 
                {
                    "horizontal": true, 
                    "thickness": 40
                }, 
                {
                    "horizontal": true, 
                    "position": 1360, 
                    "thickness": 40
                }, 
                {
                    "position": -1279, 
                    "thickness": 40, 
                    "vertical": true
                }, 
                {
                    "position": 549, 
                    "thickness": 40, 
                    "vertical": true
                }, 
                {
                    "horizontal": true, 
                    "thickness": 40
                }, 
                {
                    "horizontal": true, 
                    "position": 1360, 
                    "thickness": 40
                }, 
                {
                    "position": 544, 
                    "thickness": 40, 
                    "vertical": true
                }, 
                {
                    "position": 2372, 
                    "thickness": 40, 
                    "vertical": true
                }, 
                {
                    "horizontal": true, 
                    "thickness": 40
                }, 
                {
                    "horizontal": true, 
                    "position": 1360, 
                    "thickness": 40
                }, 
                {
                    "position": 544, 
                    "thickness": 40, 
                    "vertical": true
                }, 
                {
                    "position": 2372, 
                    "thickness": 40, 
                    "vertical": true
                }, 
                {
                    "horizontal": true, 
                    "position": 100, 
                    "thickness": 40
                }, 
                {
                    "horizontal": true, 
                    "position": 1460, 
                    "thickness": 40
                }, 
                {
                    "position": -1279, 
                    "thickness": 40, 
                    "vertical": true
                }, 
                {
                    "position": 549, 
                    "thickness": 40, 
                    "vertical": true
                }, 
                {
                    "horizontal": true, 
                    "position": 100, 
                    "thickness": 40
                }, 
                {
                    "horizontal": true, 
                    "position": 1460, 
                    "thickness": 40
                }, 
                {
                    "position": 544, 
                    "thickness": 40, 
                    "vertical": true
                }, 
                {
                    "position": 2372, 
                    "thickness": 40, 
                    "vertical": true
                }, 
                {
                    "horizontal": true, 
                    "position": 100, 
                    "thickness": 40
                }, 
                {
                    "horizontal": true, 
                    "position": 1460, 
                    "thickness": 40
                }, 
                {
                    "position": 544, 
                    "thickness": 40, 
                    "vertical": true
                }, 
                {
                    "position": 2372, 
                    "thickness": 40, 
                    "vertical": true
                }, 
                {
                    "horizontal": true, 
                    "position": -110, 
                    "thickness": 40
                }, 
                {
                    "horizontal": true, 
                    "position": 1250, 
                    "thickness": 40
                }, 
                {
                    "position": -1279, 
                    "thickness": 40, 
                    "vertical": true
                }, 
                {
                    "position": 549, 
                    "thickness": 40, 
                    "vertical": true
                }, 
                {
                    "horizontal": true, 
                    "position": -110, 
                    "thickness": 40
                }, 
                {
                    "horizontal": true, 
                    "position": 1250, 
                    "thickness": 40
                }, 
                {
                    "position": 544, 
                    "thickness": 40, 
                    "vertical": true
                }, 
                {
                    "position": 2372, 
                    "thickness": 40, 
                    "vertical": true
                }, 
                {
                    "horizontal": true, 
                    "position": -110, 
                    "thickness": 40
                }, 
                {
                    "horizontal": true, 
                    "position": 1250, 
                    "thickness": 40
                }
            ], 
            "metricsLeft": "=T+15", 
            "metricsRight": "=C-10", 
            "name": "Lt Exp Ctr"
        }, 
        {
            "advanceWidth": 772, 
            "color": "#997d87", 
            "colorFlag": 241, 
            "elements": [
                {
                    "elementData": {
                        "contours": [
                            {
                                "nodes": [
                                    "67 731", 
                                    "772 731", 
                                    "782 767", 
                                    "67 767"
                                ]
                            }, 
                            {
                                "nodes": [
                                    "67 571", 
                                    "772 571", 
                                    "782 607", 
                                    "67 607"
                                ]
                            }
                        ]
                    }, 
                    "transform": {
                        "xOffset": -42
                    }
                }
            ], 
            "flags": 0, 
            "metricsLeft": "=T+15", 
            "metricsRight": "=C-10", 
            "name": "Blk Cnd Ctr"
        }, 
        {
            "advanceWidth": 553, 
            "color": "#8fb0ff", 
            "colorFlag": 241, 
            "elements": [
                {
                    "elementData": {
                        "contours": [
                            {
                                "nodes": [
                                    "65 717", 
                                    "521 717", 
                                    "531 753", 
                                    "65 753"
                                ]
                            }, 
                            {
                                "nodes": [
                                    "65 567", 
                                    "521 567", 
                                    "531 603", 
                                    "65 603"
                                ]
                            }
                        ]
                    }, 
                    "transform": {
                        "xOffset": -40
                    }
                }
            ], 
            "flags": 0, 
            "hints": [
                {
                    "position": 137, 
                    "thickness": 280, 
                    "vertical": true
                }, 
                {
                    "position": 687, 
                    "thickness": 280, 
                    "vertical": true
                }, 
                {
                    "horizontal": true, 
                    "thickness": 40
                }, 
                {
                    "horizontal": true, 
                    "position": 1360, 
                    "thickness": 40
                }, 
                {
                    "position": -259, 
                    "thickness": 280, 
                    "vertical": true
                }, 
                {
                    "position": 292, 
                    "thickness": 280, 
                    "vertical": true
                }, 
                {
                    "horizontal": true, 
                    "thickness": 40
                }, 
                {
                    "horizontal": true, 
                    "position": 1360, 
                    "thickness": 40
                }, 
                {
                    "position": 137, 
                    "thickness": 280, 
                    "vertical": true
                }, 
                {
                    "position": 687, 
                    "thickness": 280, 
                    "vertical": true
                }, 
                {
                    "horizontal": true, 
                    "thickness": 40
                }, 
                {
                    "horizontal": true, 
                    "position": 1360, 
                    "thickness": 40
                }, 
                {
                    "position": 137, 
                    "thickness": 280, 
                    "vertical": true
                }, 
                {
                    "position": 687, 
                    "thickness": 280, 
                    "vertical": true
                }, 
                {
                    "horizontal": true, 
                    "position": 90, 
                    "thickness": 40
                }, 
                {
                    "horizontal": true, 
                    "position": 1450, 
                    "thickness": 40
                }, 
                {
                    "position": -259, 
                    "thickness": 280, 
                    "vertical": true
                }, 
                {
                    "position": 292, 
                    "thickness": 280, 
                    "vertical": true
                }, 
                {
                    "horizontal": true, 
                    "position": 90, 
                    "thickness": 40
                }, 
                {
                    "horizontal": true, 
                    "position": 1450, 
                    "thickness": 40
                }, 
                {
                    "position": 137, 
                    "thickness": 280, 
                    "vertical": true
                }, 
                {
                    "position": 687, 
                    "thickness": 280, 
                    "vertical": true
                }, 
                {
                    "horizontal": true, 
                    "position": 90, 
                    "thickness": 40
                }, 
                {
                    "horizontal": true, 
                    "position": 1450, 
                    "thickness": 40
                }, 
                {
                    "position": 137, 
                    "thickness": 280, 
                    "vertical": true
                }, 
                {
                    "position": 687, 
                    "thickness": 280, 
                    "vertical": true
                }, 
                {
                    "horizontal": true, 
                    "position": -60, 
                    "thickness": 40
                }, 
                {
                    "horizontal": true, 
                    "position": 1300, 
                    "thickness": 40
                }, 
                {
                    "position": -259, 
                    "thickness": 280, 
                    "vertical": true
                }, 
                {
                    "position": 292, 
                    "thickness": 280, 
                    "vertical": true
                }, 
                {
                    "horizontal": true, 
                    "position": -60, 
                    "thickness": 40
                }, 
                {
                    "horizontal": true, 
                    "position": 1300, 
                    "thickness": 40
                }, 
                {
                    "position": 137, 
                    "thickness": 280, 
                    "vertical": true
                }, 
                {
                    "position": 687, 
                    "thickness": 280, 
                    "vertical": true
                }, 
                {
                    "horizontal": true, 
                    "position": -60, 
                    "thickness": 40
                }, 
                {
                    "horizontal": true, 
                    "position": 1300, 
                    "thickness": 40
                }
            ], 
            "metricsLeft": "=T+15", 
            "metricsRight": "=C-10", 
            "name": "Cnd Ctr"
        }, 
        {
            "advanceWidth": 450, 
            "color": "#4e8e82", 
            "colorFlag": 241, 
            "elements": [
                {
                    "elementData": {
                        "contours": [
                            {
                                "nodes": [
                                    "80 690", 
                                    "445 690", 
                                    "455 726", 
                                    "80 726"
                                ]
                            }, 
                            {
                                "nodes": [
                                    "80 520", 
                                    "445 520", 
                                    "455 556", 
                                    "80 556"
                                ]
                            }
                        ]
                    }, 
                    "transform": {
                        "xOffset": -60
                    }
                }
            ], 
            "flags": 0, 
            "metricsLeft": "=T+15", 
            "metricsRight": "=C-10", 
            "name": "Lt Cnd Ctr"
        }, 
        {
            "active": true, 
            "advanceWidth": 1078, 
            "color": "#b69762", 
            "colorFlag": 241, 
            "elements": [
                {
                    "elementData": {
                        "contours": [
                            {
                                "nodes": [
                                    "139 737", 
                                    "1043 737", 
                                    "1051 773", 
                                    "139 773"
                                ]
                            }, 
                            {
                                "nodes": [
                                    "139 577", 
                                    "1043 577", 
                                    "1051 613", 
                                    "139 613"
                                ]
                            }
                        ]
                    }, 
                    "transform": {
                        "xOffset": -119
                    }
                }
            ], 
            "flags": 0, 
            "metricsLeft": "=T+15", 
            "metricsRight": "=C-10", 
            "name": "Blk Ctr"
        }, 
        {
            "advanceWidth": 1156, 
            "color": "#26d283", 
            "colorFlag": 241, 
            "elements": [
                {
                    "elementData": {
                        "contours": [
                            {
                                "nodes": [
                                    "141 747", 
                                    "1088 747", 
                                    "1096 783", 
                                    "141 783"
                                ]
                            }, 
                            {
                                "nodes": [
                                    "141 527", 
                                    "1088 527", 
                                    "1096 563", 
                                    "141 563"
                                ]
                            }
                        ]
                    }, 
                    "transform": {
                        "xOffset": -116
                    }
                }
            ], 
            "flags": 0, 
            "metricsLeft": "=T+15", 
            "metricsRight": "=C-10", 
            "name": "Ctr"
        }, 
        {
            "advanceWidth": 1021, 
            "color": "#9061ff", 
            "colorFlag": 241, 
            "elements": [
                {
                    "elementData": {
                        "contours": [
                            {
                                "nodes": [
                                    "181 700", 
                                    "927 700", 
                                    "937 736", 
                                    "181 736"
                                ]
                            }, 
                            {
                                "nodes": [
                                    "181 510", 
                                    "927 510", 
                                    "937 546", 
                                    "181 546"
                                ]
                            }
                        ]
                    }, 
                    "transform": {
                        "xOffset": -161
                    }
                }
            ], 
            "flags": 0, 
            "metricsLeft": "=T+15", 
            "metricsRight": "=C-10", 
            "name": "Lt Ctr"
        }, 
        {
            "advanceWidth": 1751, 
            "color": "#b07733", 
            "colorFlag": 241, 
            "elements": [
                {
                    "elementData": {
                        "contours": [
                            {
                                "nodes": [
                                    "293 725", 
                                    "1657 725", 
                                    "1689 885", 
                                    "293 885"
                                ]
                            }, 
                            {
                                "nodes": [
                                    "293 465", 
                                    "1657 465", 
                                    "1689 625", 
                                    "293 625"
                                ]
                            }
                        ]
                    }, 
                    "transform": {
                        "xOffset": -198
                    }
                }
            ], 
            "flags": 0, 
            "hints": [
                {
                    "position": 295, 
                    "thickness": 572, 
                    "vertical": true
                }, 
                {
                    "position": 2125, 
                    "thickness": 572, 
                    "vertical": true
                }, 
                {
                    "horizontal": true, 
                    "thickness": 484
                }, 
                {
                    "horizontal": true, 
                    "position": 916, 
                    "thickness": 484
                }, 
                {
                    "position": -1503, 
                    "thickness": 572, 
                    "vertical": true
                }, 
                {
                    "position": 329, 
                    "thickness": 572, 
                    "vertical": true
                }, 
                {
                    "horizontal": true, 
                    "thickness": 484
                }, 
                {
                    "horizontal": true, 
                    "position": 916, 
                    "thickness": 484
                }, 
                {
                    "position": 295, 
                    "thickness": 572, 
                    "vertical": true
                }, 
                {
                    "position": 2125, 
                    "thickness": 572, 
                    "vertical": true
                }, 
                {
                    "horizontal": true, 
                    "thickness": 484
                }, 
                {
                    "horizontal": true, 
                    "position": 916, 
                    "thickness": 484
                }, 
                {
                    "position": 295, 
                    "thickness": 572, 
                    "vertical": true
                }, 
                {
                    "position": 2125, 
                    "thickness": 572, 
                    "vertical": true
                }, 
                {
                    "horizontal": true, 
                    "thickness": 484
                }, 
                {
                    "horizontal": true, 
                    "position": 916, 
                    "thickness": 484
                }, 
                {
                    "position": -1503, 
                    "thickness": 572, 
                    "vertical": true
                }, 
                {
                    "position": 329, 
                    "thickness": 572, 
                    "vertical": true
                }, 
                {
                    "horizontal": true, 
                    "thickness": 484
                }, 
                {
                    "horizontal": true, 
                    "position": 916, 
                    "thickness": 484
                }, 
                {
                    "position": 295, 
                    "thickness": 572, 
                    "vertical": true
                }, 
                {
                    "position": 2125, 
                    "thickness": 572, 
                    "vertical": true
                }, 
                {
                    "horizontal": true, 
                    "thickness": 484
                }, 
                {
                    "horizontal": true, 
                    "position": 916, 
                    "thickness": 484
                }, 
                {
                    "position": 295, 
                    "thickness": 572, 
                    "vertical": true
                }, 
                {
                    "position": 2125, 
                    "thickness": 572, 
                    "vertical": true
                }, 
                {
                    "horizontal": true, 
                    "thickness": 484
                }, 
                {
                    "horizontal": true, 
                    "position": 916, 
                    "thickness": 484
                }, 
                {
                    "position": -1503, 
                    "thickness": 572, 
                    "vertical": true
                }, 
                {
                    "position": 329, 
                    "thickness": 572, 
                    "vertical": true
                }, 
                {
                    "horizontal": true, 
                    "thickness": 484
                }, 
                {
                    "horizontal": true, 
                    "position": 916, 
                    "thickness": 484
                }, 
                {
                    "position": 295, 
                    "thickness": 572, 
                    "vertical": true
                }, 
                {
                    "position": 2125, 
                    "thickness": 572, 
                    "vertical": true
                }, 
                {
                    "horizontal": true, 
                    "thickness": 484
                }, 
                {
                    "horizontal": true, 
                    "position": 916, 
                    "thickness": 484
                }
            ], 
            "metricsLeft": "=T+15", 
            "metricsRight": "=C-10", 
            "name": "Blk Exp"
        }, 
        {
            "advanceWidth": 1584, 
            "color": "#d2afb9", 
            "colorFlag": 241, 
            "elements": [
                {
                    "elementData": {
                        "contours": [
                            {
                                "nodes": [
                                    "209 705", 
                                    "1528 705", 
                                    "1560 865", 
                                    "209 865"
                                ]
                            }, 
                            {
                                "nodes": [
                                    "209 435", 
                                    "1528 435", 
                                    "1560 595", 
                                    "209 595"
                                ]
                            }
                        ]
                    }, 
                    "transform": {
                        "xOffset": -184
                    }
                }
            ], 
            "flags": 0, 
            "hints": [
                {
                    "position": 243, 
                    "thickness": 464, 
                    "vertical": true
                }, 
                {
                    "position": 2117, 
                    "thickness": 463.6, 
                    "vertical": true
                }, 
                {
                    "horizontal": true, 
                    "position": -14, 
                    "thickness": 244
                }, 
                {
                    "horizontal": true, 
                    "position": 1170, 
                    "thickness": 244
                }, 
                {
                    "position": 1302, 
                    "thickness": -64, 
                    "vertical": true
                }, 
                {
                    "position": 300, 
                    "thickness": -935.6, 
                    "vertical": true
                }, 
                {
                    "horizontal": true, 
                    "position": -14, 
                    "thickness": 1198
                }, 
                {
                    "horizontal": true, 
                    "position": 244, 
                    "thickness": -244
                }, 
                {
                    "position": 243, 
                    "thickness": 464, 
                    "vertical": true
                }, 
                {
                    "position": 2117, 
                    "thickness": 463.6, 
                    "vertical": true
                }, 
                {
                    "horizontal": true, 
                    "position": -14, 
                    "thickness": 244
                }, 
                {
                    "horizontal": true, 
                    "position": 1170, 
                    "thickness": 244
                }, 
                {
                    "position": 243, 
                    "thickness": 464, 
                    "vertical": true
                }, 
                {
                    "position": 2117, 
                    "thickness": 463.6, 
                    "vertical": true
                }, 
                {
                    "horizontal": true, 
                    "position": 116, 
                    "thickness": 244
                }, 
                {
                    "horizontal": true, 
                    "position": 1300, 
                    "thickness": 244
                }, 
                {
                    "position": 1302, 
                    "thickness": -64, 
                    "vertical": true
                }, 
                {
                    "position": 300, 
                    "thickness": -935.6, 
                    "vertical": true
                }, 
                {
                    "horizontal": true, 
                    "position": 116, 
                    "thickness": 1198
                }, 
                {
                    "horizontal": true, 
                    "position": 374, 
                    "thickness": -244
                }, 
                {
                    "position": 243, 
                    "thickness": 464, 
                    "vertical": true
                }, 
                {
                    "position": 2117, 
                    "thickness": 463.6, 
                    "vertical": true
                }, 
                {
                    "horizontal": true, 
                    "position": 116, 
                    "thickness": 244
                }, 
                {
                    "horizontal": true, 
                    "position": 1300, 
                    "thickness": 244
                }, 
                {
                    "position": 243, 
                    "thickness": 464, 
                    "vertical": true
                }, 
                {
                    "position": 2117, 
                    "thickness": 463.6, 
                    "vertical": true
                }, 
                {
                    "horizontal": true, 
                    "position": -154, 
                    "thickness": 244
                }, 
                {
                    "horizontal": true, 
                    "position": 1030, 
                    "thickness": 244
                }, 
                {
                    "position": 1302, 
                    "thickness": -64, 
                    "vertical": true
                }, 
                {
                    "position": 300, 
                    "thickness": -935.6, 
                    "vertical": true
                }, 
                {
                    "horizontal": true, 
                    "position": -154, 
                    "thickness": 1198
                }, 
                {
                    "horizontal": true, 
                    "position": 104, 
                    "thickness": -244
                }, 
                {
                    "position": 243, 
                    "thickness": 464, 
                    "vertical": true
                }, 
                {
                    "position": 2117, 
                    "thickness": 463.6, 
                    "vertical": true
                }, 
                {
                    "horizontal": true, 
                    "position": -154, 
                    "thickness": 244
                }, 
                {
                    "horizontal": true, 
                    "position": 1030, 
                    "thickness": 244
                }
            ], 
            "metricsLeft": "=T+15", 
            "metricsRight": "=C-10", 
            "name": "Exp"
        }, 
        {
            "advanceWidth": 1475, 
            "color": "#de4d8a", 
            "colorFlag": 241, 
            "elements": [
                {
                    "elementData": {
                        "contours": [
                            {
                                "nodes": [
                                    "226 710", 
                                    "1345 710", 
                                    "1355 746", 
                                    "226 746"
                                ]
                            }, 
                            {
                                "nodes": [
                                    "226 500", 
                                    "1345 500", 
                                    "1355 536", 
                                    "226 536"
                                ]
                            }
                        ]
                    }, 
                    "transform": {
                        "xOffset": -206
                    }
                }
            ], 
            "flags": 0, 
            "hints": [
                {
                    "position": 240, 
                    "thickness": 40, 
                    "vertical": true
                }, 
                {
                    "position": 2068, 
                    "thickness": 40, 
                    "vertical": true
                }, 
                {
                    "horizontal": true, 
                    "thickness": 40
                }, 
                {
                    "horizontal": true, 
                    "position": 1360, 
                    "thickness": 40
                }, 
                {
                    "position": -1578, 
                    "thickness": 40, 
                    "vertical": true
                }, 
                {
                    "position": 250, 
                    "thickness": 40, 
                    "vertical": true
                }, 
                {
                    "horizontal": true, 
                    "thickness": 40
                }, 
                {
                    "horizontal": true, 
                    "position": 1360, 
                    "thickness": 40
                }, 
                {
                    "position": 240, 
                    "thickness": 40, 
                    "vertical": true
                }, 
                {
                    "position": 2068, 
                    "thickness": 40, 
                    "vertical": true
                }, 
                {
                    "horizontal": true, 
                    "thickness": 40
                }, 
                {
                    "horizontal": true, 
                    "position": 1360, 
                    "thickness": 40
                }, 
                {
                    "position": 240, 
                    "thickness": 40, 
                    "vertical": true
                }, 
                {
                    "position": 2068, 
                    "thickness": 40, 
                    "vertical": true
                }, 
                {
                    "horizontal": true, 
                    "position": 100, 
                    "thickness": 40
                }, 
                {
                    "horizontal": true, 
                    "position": 1460, 
                    "thickness": 40
                }, 
                {
                    "position": -1578, 
                    "thickness": 40, 
                    "vertical": true
                }, 
                {
                    "position": 250, 
                    "thickness": 40, 
                    "vertical": true
                }, 
                {
                    "horizontal": true, 
                    "position": 100, 
                    "thickness": 40
                }, 
                {
                    "horizontal": true, 
                    "position": 1460, 
                    "thickness": 40
                }, 
                {
                    "position": 240, 
                    "thickness": 40, 
                    "vertical": true
                }, 
                {
                    "position": 2068, 
                    "thickness": 40, 
                    "vertical": true
                }, 
                {
                    "horizontal": true, 
                    "position": 100, 
                    "thickness": 40
                }, 
                {
                    "horizontal": true, 
                    "position": 1460, 
                    "thickness": 40
                }, 
                {
                    "position": 240, 
                    "thickness": 40, 
                    "vertical": true
                }, 
                {
                    "position": 2068, 
                    "thickness": 40, 
                    "vertical": true
                }, 
                {
                    "horizontal": true, 
                    "position": -110, 
                    "thickness": 40
                }, 
                {
                    "horizontal": true, 
                    "position": 1250, 
                    "thickness": 40
                }, 
                {
                    "position": -1578, 
                    "thickness": 40, 
                    "vertical": true
                }, 
                {
                    "position": 250, 
                    "thickness": 40, 
                    "vertical": true
                }, 
                {
                    "horizontal": true, 
                    "position": -110, 
                    "thickness": 40
                }, 
                {
                    "horizontal": true, 
                    "position": 1250, 
                    "thickness": 40
                }, 
                {
                    "position": 240, 
                    "thickness": 40, 
                    "vertical": true
                }, 
                {
                    "position": 2068, 
                    "thickness": 40, 
                    "vertical": true
                }, 
                {
                    "horizontal": true, 
                    "position": -110, 
                    "thickness": 40
                }, 
                {
                    "horizontal": true, 
                    "position": 1250, 
                    "thickness": 40
                }
            ], 
            "metricsLeft": "=T+15", 
            "metricsRight": "=C-10", 
            "name": "Lt Exp"
        }, 
        {
            "advanceWidth": 774, 
            "color": "#3989c2", 
            "colorFlag": 241, 
            "elements": [
                {
                    "elementData": {
                        "contours": [
                            {
                                "nodes": [
                                    "98 690", 
                                    "770 690", 
                                    "802 850", 
                                    "98 850"
                                ]
                            }, 
                            {
                                "nodes": [
                                    "98 460", 
                                    "770 460", 
                                    "802 620", 
                                    "98 620"
                                ]
                            }
                        ]
                    }, 
                    "transform": {
                        "xOffset": -60.14
                    }
                }
            ], 
            "flags": 0, 
            "metricsLeft": "=T+15", 
            "metricsRight": "=C-10", 
            "name": "Blk Cnd"
        }, 
        {
            "advanceWidth": 519, 
            "color": "#1f964d", 
            "colorFlag": 241, 
            "elements": [
                {
                    "elementData": {
                        "contours": [
                            {
                                "nodes": [
                                    "66 690", 
                                    "496 690", 
                                    "528 850", 
                                    "66 850"
                                ]
                            }, 
                            {
                                "nodes": [
                                    "66 460", 
                                    "496 460", 
                                    "528 620", 
                                    "66 620"
                                ]
                            }
                        ]
                    }, 
                    "transform": {
                        "xOffset": -46
                    }
                }
            ], 
            "flags": 0, 
            "hints": [
                {
                    "position": 76, 
                    "thickness": 264, 
                    "vertical": true
                }, 
                {
                    "position": 500, 
                    "thickness": 264, 
                    "vertical": true
                }, 
                {
                    "horizontal": true, 
                    "position": -18, 
                    "thickness": 244
                }, 
                {
                    "horizontal": true, 
                    "position": 1174, 
                    "thickness": 244
                }, 
                {
                    "position": 597, 
                    "thickness": -264, 
                    "vertical": true
                }, 
                {
                    "position": 91, 
                    "thickness": -182.5, 
                    "vertical": true
                }, 
                {
                    "horizontal": true, 
                    "position": -18, 
                    "thickness": 1210
                }, 
                {
                    "horizontal": true, 
                    "position": 244, 
                    "thickness": -244
                }, 
                {
                    "position": 76, 
                    "thickness": 264, 
                    "vertical": true
                }, 
                {
                    "position": 500, 
                    "thickness": 264, 
                    "vertical": true
                }, 
                {
                    "horizontal": true, 
                    "position": -18, 
                    "thickness": 244
                }, 
                {
                    "horizontal": true, 
                    "position": 1174, 
                    "thickness": 244
                }, 
                {
                    "position": 76, 
                    "thickness": 264, 
                    "vertical": true
                }, 
                {
                    "position": 500, 
                    "thickness": 264, 
                    "vertical": true
                }, 
                {
                    "horizontal": true, 
                    "position": 102, 
                    "thickness": 244
                }, 
                {
                    "horizontal": true, 
                    "position": 1294, 
                    "thickness": 244
                }, 
                {
                    "position": 597, 
                    "thickness": -264, 
                    "vertical": true
                }, 
                {
                    "position": 91, 
                    "thickness": -182.5, 
                    "vertical": true
                }, 
                {
                    "horizontal": true, 
                    "position": 102, 
                    "thickness": 1210
                }, 
                {
                    "horizontal": true, 
                    "position": 364, 
                    "thickness": -244
                }, 
                {
                    "position": 76, 
                    "thickness": 264, 
                    "vertical": true
                }, 
                {
                    "position": 500, 
                    "thickness": 264, 
                    "vertical": true
                }, 
                {
                    "horizontal": true, 
                    "position": 102, 
                    "thickness": 244
                }, 
                {
                    "horizontal": true, 
                    "position": 1294, 
                    "thickness": 244
                }, 
                {
                    "position": 76, 
                    "thickness": 264, 
                    "vertical": true
                }, 
                {
                    "position": 500, 
                    "thickness": 264, 
                    "vertical": true
                }, 
                {
                    "horizontal": true, 
                    "position": -128, 
                    "thickness": 244
                }, 
                {
                    "horizontal": true, 
                    "position": 1064, 
                    "thickness": 244
                }, 
                {
                    "position": 597, 
                    "thickness": -264, 
                    "vertical": true
                }, 
                {
                    "position": 91, 
                    "thickness": -182.5, 
                    "vertical": true
                }, 
                {
                    "horizontal": true, 
                    "position": -128, 
                    "thickness": 1210
                }, 
                {
                    "horizontal": true, 
                    "position": 134, 
                    "thickness": -244
                }, 
                {
                    "position": 76, 
                    "thickness": 264, 
                    "vertical": true
                }, 
                {
                    "position": 500, 
                    "thickness": 264, 
                    "vertical": true
                }, 
                {
                    "horizontal": true, 
                    "position": -128, 
                    "thickness": 244
                }, 
                {
                    "horizontal": true, 
                    "position": 1064, 
                    "thickness": 244
                }
            ], 
            "metricsLeft": "=T+15", 
            "metricsRight": "=C-10", 
            "name": "Cnd"
        }, 
        {
            "advanceWidth": 450, 
            "color": "#fe4a46", 
            "colorFlag": 241, 
            "elements": [
                {
                    "elementData": {
                        "contours": [
                            {
                                "nodes": [
                                    "80 690", 
                                    "445 690", 
                                    "455 726", 
                                    "80 726"
                                ]
                            }, 
                            {
                                "nodes": [
                                    "80 520", 
                                    "445 520", 
                                    "455 556", 
                                    "80 556"
                                ]
                            }
                        ]
                    }, 
                    "transform": {
                        "xOffset": -60
                    }
                }
            ], 
            "flags": 0, 
            "metricsLeft": "=T+15", 
            "metricsRight": "=C-10", 
            "name": "Lt Cnd"
        }, 
        {
            "advanceWidth": 1085, 
            "color": "#ff34ff", 
            "colorFlag": 241, 
            "elements": [
                {
                    "elementData": {
                        "contours": [
                            {
                                "nodes": [
                                    "191 695", 
                                    "1061 695", 
                                    "1093 855", 
                                    "191 855"
                                ]
                            }, 
                            {
                                "nodes": [
                                    "191 465", 
                                    "1061 465", 
                                    "1093 625", 
                                    "191 625"
                                ]
                            }
                        ]
                    }, 
                    "transform": {
                        "xOffset": -124.57
                    }
                }
            ], 
            "flags": 0, 
            "metricsLeft": "=T+15", 
            "metricsRight": "=C-10", 
            "name": "Blk"
        }, 
        {
            "advanceWidth": 1130, 
            "color": "#00cce5", 
            "colorFlag": 241, 
            "elements": [
                {
                    "active": true, 
                    "elementData": {
                        "contours": [
                            {
                                "nodes": [
                                    "131 705", 
                                    "1066 705", 
                                    "1098 865", 
                                    "131 865"
                                ]
                            }, 
                            {
                                "nodes": [
                                    "131 455", 
                                    "1066 455", 
                                    "1098 615", 
                                    "131 615"
                                ]
                            }
                        ]
                    }, 
                    "transform": {
                        "xOffset": -96
                    }
                }
            ], 
            "flags": 0, 
            "hints": [
                {
                    "position": 1205, 
                    "thickness": -264, 
                    "vertical": true
                }, 
                {
                    "position": 301, 
                    "thickness": -408, 
                    "vertical": true
                }, 
                {
                    "horizontal": true, 
                    "position": -14, 
                    "thickness": 1198
                }, 
                {
                    "horizontal": true, 
                    "position": 244, 
                    "thickness": -244
                }, 
                {
                    "position": 255, 
                    "thickness": 264, 
                    "vertical": true
                }, 
                {
                    "position": 1303, 
                    "thickness": 264, 
                    "vertical": true
                }, 
                {
                    "horizontal": true, 
                    "position": -14, 
                    "thickness": 244
                }, 
                {
                    "horizontal": true, 
                    "position": 1170, 
                    "thickness": 244
                }, 
                {
                    "position": 1205, 
                    "thickness": -264, 
                    "vertical": true
                }, 
                {
                    "position": 301, 
                    "thickness": -408, 
                    "vertical": true
                }, 
                {
                    "horizontal": true, 
                    "position": 116, 
                    "thickness": 1198
                }, 
                {
                    "horizontal": true, 
                    "position": 374, 
                    "thickness": -244
                }, 
                {
                    "position": 255, 
                    "thickness": 264, 
                    "vertical": true
                }, 
                {
                    "position": 1303, 
                    "thickness": 264, 
                    "vertical": true
                }, 
                {
                    "horizontal": true, 
                    "position": 116, 
                    "thickness": 244
                }, 
                {
                    "horizontal": true, 
                    "position": 1300, 
                    "thickness": 244
                }, 
                {
                    "position": 1205, 
                    "thickness": -264, 
                    "vertical": true
                }, 
                {
                    "position": 301, 
                    "thickness": -408, 
                    "vertical": true
                }, 
                {
                    "horizontal": true, 
                    "position": -134, 
                    "thickness": 1198
                }, 
                {
                    "horizontal": true, 
                    "position": 124, 
                    "thickness": -244
                }, 
                {
                    "position": 255, 
                    "thickness": 264, 
                    "vertical": true
                }, 
                {
                    "position": 1303, 
                    "thickness": 264, 
                    "vertical": true
                }, 
                {
                    "horizontal": true, 
                    "position": -134, 
                    "thickness": 244
                }, 
                {
                    "horizontal": true, 
                    "position": 1050, 
                    "thickness": 244
                }
            ], 
            "metricsLeft": "=T+15", 
            "metricsRight": "=C-10", 
            "name": "Medium"
        }, 
        {
            "advanceWidth": 1021, 
            "color": "#bac000", 
            "colorFlag": 241, 
            "elements": [
                {
                    "elementData": {
                        "contours": [
                            {
                                "nodes": [
                                    "181 700", 
                                    "927 700", 
                                    "937 736", 
                                    "181 736"
                                ]
                            }, 
                            {
                                "nodes": [
                                    "181 510", 
                                    "927 510", 
                                    "937 546", 
                                    "181 546"
                                ]
                            }
                        ]
                    }, 
                    "transform": {
                        "xOffset": -161
                    }
                }
            ], 
            "flags": 0, 
            "guidelines": [
                {
                    "horizontal": true, 
                    "position": 1000
                }
            ], 
            "metricsLeft": "=T+15", 
            "metricsRight": "=C-10", 
            "name": "Lt"
        }
    ], 
    "name": "currency-double-bar"
}