{
    "colorFlag": 210, 
    "layers": [
        {
            "advanceWidth": 2635, 
            "anchors": [
                {
                    "name": "top", 
                    "point": "1211 1150"
                }
            ], 
            "autoRecipe": "=uni0438+uni0304@top", 
            "color": "#b9baa2", 
            "colorFlag": 210, 
            "elements": [
                {
                    "component": {
                        "glyphName": "uni0438"
                    }, 
                    "locked": true
                }, 
                {
                    "component": {
                        "glyphName": "uni0304"
                    }, 
                    "locked": true, 
                    "nonSpacing": true, 
                    "transform": {
                        "xOffset": 1211
                    }
                }
            ], 
            "flags": 16, 
            "name": "Blk Exp Ctr"
        }, 
        {
            "advanceWidth": 2276, 
            "anchors": [
                {
                    "name": "top", 
                    "point": "1090 1150"
                }
            ], 
            "autoRecipe": "=uni0438+uni0304@top", 
            "color": "#809693", 
            "colorFlag": 210, 
            "elements": [
                {
                    "component": {
                        "glyphName": "uni0438"
                    }, 
                    "locked": true
                }, 
                {
                    "component": {
                        "glyphName": "uni0304"
                    }, 
                    "locked": true, 
                    "nonSpacing": true, 
                    "transform": {
                        "xOffset": 1090
                    }
                }
            ], 
            "flags": 16, 
            "name": "Exp Ctr"
        }, 
        {
            "advanceWidth": 2042, 
            "anchors": [
                {
                    "name": "top", 
                    "point": "1023 1150"
                }
            ], 
            "autoRecipe": "=uni0438+uni0304@top", 
            "color": "#c8675e", 
            "colorFlag": 210, 
            "elements": [
                {
                    "component": {
                        "glyphName": "uni0438"
                    }, 
                    "locked": true
                }, 
                {
                    "component": {
                        "glyphName": "uni0304"
                    }, 
                    "locked": true, 
                    "nonSpacing": true, 
                    "transform": {
                        "xOffset": 1023, 
                        "yOffset": -50
                    }
                }
            ], 
            "flags": 16, 
            "name": "Lt Exp Ctr"
        }, 
        {
            "advanceWidth": 1353, 
            "anchors": [
                {
                    "name": "top", 
                    "point": "675 1150"
                }
            ], 
            "autoRecipe": "=uni0438+uni0304@top", 
            "color": "#997d87", 
            "colorFlag": 210, 
            "elements": [
                {
                    "component": {
                        "glyphName": "uni0438"
                    }, 
                    "locked": true
                }, 
                {
                    "component": {
                        "glyphName": "uni0304"
                    }, 
                    "locked": true, 
                    "nonSpacing": true, 
                    "transform": {
                        "xOffset": 675, 
                        "yOffset": -50
                    }
                }
            ], 
            "flags": 16, 
            "name": "Blk Cnd Ctr"
        }, 
        {
            "advanceWidth": 808, 
            "anchors": [
                {
                    "name": "top", 
                    "point": "408 1150"
                }
            ], 
            "autoRecipe": "=uni0438+uni0304@top", 
            "color": "#8fb0ff", 
            "colorFlag": 210, 
            "elements": [
                {
                    "component": {
                        "glyphName": "uni0438"
                    }, 
                    "locked": true
                }, 
                {
                    "component": {
                        "glyphName": "uni0304"
                    }, 
                    "locked": true, 
                    "nonSpacing": true, 
                    "transform": {
                        "xOffset": 408, 
                        "yOffset": -50
                    }
                }
            ], 
            "flags": 16, 
            "name": "Cnd Ctr"
        }, 
        {
            "advanceWidth": 501, 
            "anchors": [
                {
                    "name": "top", 
                    "point": "254 1150"
                }
            ], 
            "autoRecipe": "=uni0438+uni0304@top", 
            "color": "#4e8e82", 
            "colorFlag": 210, 
            "elements": [
                {
                    "component": {
                        "glyphName": "uni0438"
                    }, 
                    "locked": true
                }, 
                {
                    "component": {
                        "glyphName": "uni0304"
                    }, 
                    "locked": true, 
                    "nonSpacing": true, 
                    "transform": {
                        "xOffset": 254, 
                        "yOffset": -50
                    }
                }
            ], 
            "flags": 16, 
            "name": "Lt Cnd Ctr"
        }, 
        {
            "advanceWidth": 1695, 
            "anchors": [
                {
                    "name": "top", 
                    "point": "844 1150"
                }
            ], 
            "autoRecipe": "=uni0438+uni0304@top", 
            "color": "#b69762", 
            "colorFlag": 210, 
            "elements": [
                {
                    "component": {
                        "glyphName": "uni0438"
                    }, 
                    "locked": true
                }, 
                {
                    "component": {
                        "glyphName": "uni0304"
                    }, 
                    "locked": true, 
                    "nonSpacing": true, 
                    "transform": {
                        "xOffset": 844, 
                        "yOffset": -50
                    }
                }
            ], 
            "flags": 16, 
            "name": "Blk Ctr"
        }, 
        {
            "advanceWidth": 1406, 
            "anchors": [
                {
                    "name": "top", 
                    "point": "707 1150"
                }
            ], 
            "autoRecipe": "=uni0438+uni0304@top", 
            "color": "#26d283", 
            "colorFlag": 210, 
            "elements": [
                {
                    "component": {
                        "glyphName": "uni0438"
                    }, 
                    "locked": true
                }, 
                {
                    "component": {
                        "glyphName": "uni0304"
                    }, 
                    "locked": true, 
                    "nonSpacing": true, 
                    "transform": {
                        "xOffset": 707, 
                        "yOffset": -50
                    }
                }
            ], 
            "flags": 16, 
            "name": "Ctr"
        }, 
        {
            "advanceWidth": 1331, 
            "anchors": [
                {
                    "name": "top", 
                    "point": "669.50 1150"
                }
            ], 
            "autoRecipe": "=uni0438+uni0304@top", 
            "color": "#9061ff", 
            "colorFlag": 210, 
            "elements": [
                {
                    "component": {
                        "glyphName": "uni0438"
                    }, 
                    "locked": true
                }, 
                {
                    "component": {
                        "glyphName": "uni0304"
                    }, 
                    "locked": true, 
                    "nonSpacing": true, 
                    "transform": {
                        "xOffset": 669.5, 
                        "yOffset": -50
                    }
                }
            ], 
            "flags": 16, 
            "name": "Lt Ctr"
        }, 
        {
            "advanceWidth": 2443, 
            "anchors": [
                {
                    "name": "top", 
                    "point": "1226 1150"
                }
            ], 
            "autoRecipe": "=uni0438+uni0304@top", 
            "color": "#b07733", 
            "colorFlag": 210, 
            "elements": [
                {
                    "component": {
                        "glyphName": "uni0438"
                    }, 
                    "locked": true
                }, 
                {
                    "component": {
                        "glyphName": "uni0304"
                    }, 
                    "locked": true, 
                    "nonSpacing": true, 
                    "transform": {
                        "xOffset": 1226
                    }
                }
            ], 
            "flags": 16, 
            "name": "Blk Exp"
        }, 
        {
            "advanceWidth": 2101, 
            "anchors": [
                {
                    "name": "top", 
                    "point": "1055 1150"
                }
            ], 
            "autoRecipe": "=uni0438+uni0304@top", 
            "color": "#d2afb9", 
            "colorFlag": 210, 
            "elements": [
                {
                    "component": {
                        "glyphName": "uni0438"
                    }, 
                    "locked": true
                }, 
                {
                    "component": {
                        "glyphName": "uni0304"
                    }, 
                    "locked": true, 
                    "nonSpacing": true, 
                    "transform": {
                        "xOffset": 1055
                    }
                }
            ], 
            "flags": 16, 
            "name": "Exp"
        }, 
        {
            "advanceWidth": 2042, 
            "anchors": [
                {
                    "name": "top", 
                    "point": "1023 1150"
                }
            ], 
            "autoRecipe": "=uni0438+uni0304@top", 
            "color": "#de4d8a", 
            "colorFlag": 210, 
            "elements": [
                {
                    "component": {
                        "glyphName": "uni0438"
                    }, 
                    "locked": true
                }, 
                {
                    "component": {
                        "glyphName": "uni0304"
                    }, 
                    "locked": true, 
                    "nonSpacing": true, 
                    "transform": {
                        "xOffset": 1025, 
                        "yOffset": -50
                    }
                }
            ], 
            "flags": 16, 
            "name": "Lt Exp"
        }, 
        {
            "advanceWidth": 1335, 
            "anchors": [
                {
                    "name": "top", 
                    "point": "669 1150"
                }
            ], 
            "autoRecipe": "=uni0438+uni0304@top", 
            "color": "#3989c2", 
            "colorFlag": 210, 
            "elements": [
                {
                    "component": {
                        "glyphName": "uni0438"
                    }, 
                    "locked": true
                }, 
                {
                    "component": {
                        "glyphName": "uni0304"
                    }, 
                    "locked": true, 
                    "nonSpacing": true, 
                    "transform": {
                        "xOffset": 669, 
                        "yOffset": -24
                    }
                }
            ], 
            "flags": 16, 
            "name": "Blk Cnd"
        }, 
        {
            "advanceWidth": 771, 
            "anchors": [
                {
                    "name": "top", 
                    "point": "390 1150"
                }
            ], 
            "autoRecipe": "=uni0438+uni0304@top", 
            "color": "#1f964d", 
            "colorFlag": 210, 
            "elements": [
                {
                    "component": {
                        "glyphName": "uni0438"
                    }, 
                    "locked": true
                }, 
                {
                    "component": {
                        "glyphName": "uni0304"
                    }, 
                    "locked": true, 
                    "nonSpacing": true, 
                    "transform": {
                        "xOffset": 390
                    }
                }
            ], 
            "flags": 16, 
            "name": "Cnd"
        }, 
        {
            "advanceWidth": 501, 
            "anchors": [
                {
                    "name": "top", 
                    "point": "254 1150"
                }
            ], 
            "autoRecipe": "=uni0438+uni0304@top", 
            "color": "#fe4a46", 
            "colorFlag": 210, 
            "elements": [
                {
                    "component": {
                        "glyphName": "uni0438"
                    }, 
                    "locked": true
                }, 
                {
                    "component": {
                        "glyphName": "uni0304"
                    }, 
                    "locked": true, 
                    "nonSpacing": true, 
                    "transform": {
                        "xOffset": 254, 
                        "yOffset": -50
                    }
                }
            ], 
            "flags": 16, 
            "name": "Lt Cnd"
        }, 
        {
            "advanceWidth": 1595, 
            "anchors": [
                {
                    "name": "top", 
                    "point": "799 1150"
                }
            ], 
            "autoRecipe": "=uni0438+uni0304@top", 
            "color": "#ff34ff", 
            "colorFlag": 210, 
            "elements": [
                {
                    "component": {
                        "glyphName": "uni0438"
                    }, 
                    "locked": true
                }, 
                {
                    "component": {
                        "glyphName": "uni0304"
                    }, 
                    "locked": true, 
                    "nonSpacing": true, 
                    "transform": {
                        "xOffset": 799, 
                        "yOffset": -24
                    }
                }
            ], 
            "flags": 16, 
            "name": "Blk"
        }, 
        {
            "advanceWidth": 1420, 
            "anchors": [
                {
                    "name": "top", 
                    "point": "714 1150"
                }
            ], 
            "autoRecipe": "=uni0438+uni0304@top", 
            "color": "#00cce5", 
            "colorFlag": 210, 
            "elements": [
                {
                    "component": {
                        "glyphName": "uni0438"
                    }, 
                    "locked": true
                }, 
                {
                    "component": {
                        "glyphName": "uni0304"
                    }, 
                    "locked": true, 
                    "nonSpacing": true, 
                    "transform": {
                        "xOffset": 714
                    }
                }
            ], 
            "flags": 16, 
            "name": "Medium"
        }, 
        {
            "advanceWidth": 1331, 
            "anchors": [
                {
                    "name": "top", 
                    "point": "670 1150"
                }
            ], 
            "autoRecipe": "=uni0438+uni0304@top", 
            "color": "#bac000", 
            "colorFlag": 210, 
            "elements": [
                {
                    "component": {
                        "glyphName": "uni0438"
                    }, 
                    "locked": true
                }, 
                {
                    "component": {
                        "glyphName": "uni0304"
                    }, 
                    "locked": true, 
                    "nonSpacing": true, 
                    "transform": {
                        "xOffset": 670, 
                        "yOffset": -50
                    }
                }
            ], 
            "flags": 16, 
            "name": "Lt"
        }
    ], 
    "name": "uni04E3", 
    "tags": [
        "cyr", 
        "V"
    ], 
    "unicode": "04e3"
}