{
    "lastModified": "2019-10-14 06:59:24", 
    "layers": [
        {
            "advanceWidth": 2706, 
            "anchors": [
                {
                    "name": "top", 
                    "point": "1470 1550"
                }, 
                {
                    "name": "bottom", 
                    "point": "1460 -150"
                }
            ], 
            "autoRecipe": "=Y+uni0308.case@top", 
            "color": "#b9baa2", 
            "elements": [
                {
                    "component": {
                        "glyphName": "Y"
                    }, 
                    "locked": true
                }, 
                {
                    "component": {
                        "glyphName": "uni0308.case"
                    }, 
                    "locked": true, 
                    "nonSpacing": true, 
                    "transform": {
                        "xOffset": 1470, 
                        "yOffset": 378
                    }
                }
            ], 
            "flags": 16, 
            "name": "Blk Exp Ctr"
        }, 
        {
            "advanceWidth": 2351, 
            "anchors": [
                {
                    "name": "top", 
                    "point": "1220 1550"
                }, 
                {
                    "name": "bottom", 
                    "point": "1220 -150"
                }
            ], 
            "autoRecipe": "=Y+uni0308.case@top", 
            "color": "#809693", 
            "elements": [
                {
                    "component": {
                        "glyphName": "Y"
                    }, 
                    "locked": true
                }, 
                {
                    "component": {
                        "glyphName": "uni0308.case"
                    }, 
                    "locked": true, 
                    "nonSpacing": true, 
                    "transform": {
                        "xOffset": 1220, 
                        "yOffset": 400
                    }
                }
            ], 
            "flags": 16, 
            "name": "Exp Ctr"
        }, 
        {
            "advanceWidth": 2218, 
            "anchors": [
                {
                    "name": "top", 
                    "point": "1109 1550"
                }, 
                {
                    "name": "bottom", 
                    "point": "1109 -150"
                }
            ], 
            "autoRecipe": "=Y+uni0308.case@top", 
            "color": "#c8675e", 
            "elements": [
                {
                    "component": {
                        "glyphName": "Y"
                    }, 
                    "locked": true
                }, 
                {
                    "component": {
                        "glyphName": "uni0308.case"
                    }, 
                    "locked": true, 
                    "nonSpacing": true, 
                    "transform": {
                        "xOffset": 1109, 
                        "yOffset": 400
                    }
                }
            ], 
            "flags": 16, 
            "name": "Lt Exp Ctr"
        }, 
        {
            "advanceWidth": 1316, 
            "anchors": [
                {
                    "name": "top", 
                    "point": "669 1550"
                }, 
                {
                    "name": "bottom", 
                    "point": "669 -150"
                }
            ], 
            "autoRecipe": "=Y+uni0308.case@top", 
            "color": "#997d87", 
            "elements": [
                {
                    "component": {
                        "glyphName": "Y"
                    }, 
                    "locked": true
                }, 
                {
                    "component": {
                        "glyphName": "uni0308.case"
                    }, 
                    "locked": true, 
                    "nonSpacing": true, 
                    "transform": {
                        "xOffset": 669, 
                        "yOffset": 378
                    }
                }
            ], 
            "flags": 16, 
            "name": "Blk Cnd Ctr"
        }, 
        {
            "advanceWidth": 793, 
            "anchors": [
                {
                    "name": "top", 
                    "point": "397 1550"
                }, 
                {
                    "name": "bottom", 
                    "point": "397 -150"
                }
            ], 
            "autoRecipe": "=Y+uni0308.case@top", 
            "color": "#8fb0ff", 
            "elements": [
                {
                    "component": {
                        "glyphName": "Y"
                    }, 
                    "locked": true
                }, 
                {
                    "component": {
                        "glyphName": "uni0308.case"
                    }, 
                    "locked": true, 
                    "nonSpacing": true, 
                    "transform": {
                        "xOffset": 397, 
                        "yOffset": 400
                    }
                }
            ], 
            "flags": 16, 
            "name": "Cnd Ctr"
        }, 
        {
            "advanceWidth": 514, 
            "anchors": [
                {
                    "name": "top", 
                    "point": "257 1550"
                }, 
                {
                    "name": "bottom", 
                    "point": "257 -150"
                }
            ], 
            "autoRecipe": "=Y+uni0308.case@top", 
            "color": "#4e8e82", 
            "elements": [
                {
                    "component": {
                        "glyphName": "Y"
                    }, 
                    "locked": true
                }, 
                {
                    "component": {
                        "glyphName": "uni0308.case"
                    }, 
                    "locked": true, 
                    "nonSpacing": true, 
                    "transform": {
                        "xOffset": 257, 
                        "yOffset": 400
                    }
                }
            ], 
            "flags": 16, 
            "name": "Lt Cnd Ctr"
        }, 
        {
            "advanceWidth": 1897, 
            "anchors": [
                {
                    "name": "top", 
                    "point": "1081 1550"
                }, 
                {
                    "name": "bottom", 
                    "point": "994 -150"
                }
            ], 
            "autoRecipe": "=Y+uni0308.case@top", 
            "color": "#b69762", 
            "elements": [
                {
                    "component": {
                        "glyphName": "Y"
                    }, 
                    "locked": true
                }, 
                {
                    "component": {
                        "glyphName": "uni0308.case"
                    }, 
                    "locked": true, 
                    "nonSpacing": true, 
                    "transform": {
                        "xOffset": 1081, 
                        "yOffset": 378
                    }
                }
            ], 
            "flags": 16, 
            "name": "Blk Ctr"
        }, 
        {
            "advanceWidth": 1559, 
            "anchors": [
                {
                    "name": "top", 
                    "point": "816 1556"
                }, 
                {
                    "name": "bottom", 
                    "point": "816 -150"
                }
            ], 
            "autoRecipe": "=Y+uni0308.case@top", 
            "color": "#26d283", 
            "elements": [
                {
                    "component": {
                        "glyphName": "Y"
                    }, 
                    "locked": true
                }, 
                {
                    "component": {
                        "glyphName": "uni0308.case"
                    }, 
                    "locked": true, 
                    "nonSpacing": true, 
                    "transform": {
                        "xOffset": 816, 
                        "yOffset": 406
                    }
                }
            ], 
            "flags": 16, 
            "name": "Ctr"
        }, 
        {
            "advanceWidth": 1333, 
            "anchors": [
                {
                    "name": "top", 
                    "point": "667 1550"
                }, 
                {
                    "name": "bottom", 
                    "point": "667 -150"
                }
            ], 
            "autoRecipe": "=Y+uni0308.case@top", 
            "color": "#9061ff", 
            "elements": [
                {
                    "component": {
                        "glyphName": "Y"
                    }, 
                    "locked": true
                }, 
                {
                    "component": {
                        "glyphName": "uni0308.case"
                    }, 
                    "locked": true, 
                    "nonSpacing": true, 
                    "transform": {
                        "xOffset": 667, 
                        "yOffset": 400
                    }
                }
            ], 
            "flags": 16, 
            "name": "Lt Ctr"
        }, 
        {
            "advanceWidth": 2863, 
            "anchors": [
                {
                    "name": "top", 
                    "point": "1437 1550"
                }, 
                {
                    "name": "bottom", 
                    "point": "1432 -150"
                }
            ], 
            "autoRecipe": "=Y+uni0308.case@top", 
            "color": "#b07733", 
            "elements": [
                {
                    "component": {
                        "glyphName": "Y"
                    }, 
                    "locked": true
                }, 
                {
                    "component": {
                        "glyphName": "uni0308.case"
                    }, 
                    "locked": true, 
                    "nonSpacing": true, 
                    "transform": {
                        "xOffset": 1437, 
                        "yOffset": 378
                    }
                }
            ], 
            "flags": 16, 
            "name": "Blk Exp"
        }, 
        {
            "advanceWidth": 2536, 
            "anchors": [
                {
                    "name": "top", 
                    "point": "1268 1550"
                }, 
                {
                    "name": "bottom", 
                    "point": "1268 -150"
                }
            ], 
            "autoRecipe": "=Y+uni0308.case@top", 
            "color": "#d2afb9", 
            "elements": [
                {
                    "component": {
                        "glyphName": "Y"
                    }, 
                    "locked": true
                }, 
                {
                    "component": {
                        "glyphName": "uni0308.case"
                    }, 
                    "locked": true, 
                    "nonSpacing": true, 
                    "transform": {
                        "xOffset": 1268, 
                        "yOffset": 400
                    }
                }
            ], 
            "flags": 16, 
            "name": "Exp"
        }, 
        {
            "advanceWidth": 2218, 
            "anchors": [
                {
                    "name": "top", 
                    "point": "1109 1550"
                }, 
                {
                    "name": "bottom", 
                    "point": "1109 -150"
                }
            ], 
            "autoRecipe": "=Y+uni0308.case@top", 
            "color": "#de4d8a", 
            "elements": [
                {
                    "component": {
                        "glyphName": "Y"
                    }, 
                    "locked": true
                }, 
                {
                    "component": {
                        "glyphName": "uni0308.case"
                    }, 
                    "locked": true, 
                    "nonSpacing": true, 
                    "transform": {
                        "xOffset": 1109, 
                        "yOffset": 400
                    }
                }
            ], 
            "flags": 16, 
            "name": "Lt Exp"
        }, 
        {
            "advanceWidth": 1388, 
            "anchors": [
                {
                    "name": "top", 
                    "point": "704 1550"
                }, 
                {
                    "name": "bottom", 
                    "point": "704 -150"
                }
            ], 
            "autoRecipe": "=Y+uni0308.case@top", 
            "color": "#3989c2", 
            "elements": [
                {
                    "component": {
                        "glyphName": "Y"
                    }, 
                    "locked": true
                }, 
                {
                    "component": {
                        "glyphName": "uni0308.case"
                    }, 
                    "locked": true, 
                    "nonSpacing": true, 
                    "transform": {
                        "xOffset": 704, 
                        "yOffset": 378
                    }
                }
            ], 
            "flags": 16, 
            "name": "Blk Cnd"
        }, 
        {
            "advanceWidth": 774, 
            "anchors": [
                {
                    "name": "top", 
                    "point": "387 1550"
                }, 
                {
                    "name": "bottom", 
                    "point": "387 -150"
                }
            ], 
            "autoRecipe": "=Y+uni0308.case@top", 
            "color": "#1f964d", 
            "elements": [
                {
                    "component": {
                        "glyphName": "Y"
                    }, 
                    "locked": true
                }, 
                {
                    "component": {
                        "glyphName": "uni0308.case"
                    }, 
                    "locked": true, 
                    "nonSpacing": true, 
                    "transform": {
                        "xOffset": 387, 
                        "yOffset": 400
                    }
                }
            ], 
            "flags": 16, 
            "name": "Cnd"
        }, 
        {
            "advanceWidth": 514, 
            "anchors": [
                {
                    "name": "top", 
                    "point": "257 1550"
                }, 
                {
                    "name": "bottom", 
                    "point": "257 -150"
                }
            ], 
            "autoRecipe": "=Y+uni0308.case@top", 
            "color": "#fe4a46", 
            "elements": [
                {
                    "component": {
                        "glyphName": "Y"
                    }, 
                    "locked": true
                }, 
                {
                    "component": {
                        "glyphName": "uni0308.case"
                    }, 
                    "locked": true, 
                    "nonSpacing": true, 
                    "transform": {
                        "xOffset": 257, 
                        "yOffset": 400
                    }
                }
            ], 
            "flags": 16, 
            "name": "Lt Cnd"
        }, 
        {
            "advanceWidth": 1905, 
            "anchors": [
                {
                    "name": "top", 
                    "point": "953 1550"
                }, 
                {
                    "name": "bottom", 
                    "point": "953 -150"
                }
            ], 
            "autoRecipe": "=Y+uni0308.case@top", 
            "color": "#ff34ff", 
            "elements": [
                {
                    "component": {
                        "glyphName": "Y"
                    }, 
                    "locked": true
                }, 
                {
                    "component": {
                        "glyphName": "uni0308.case"
                    }, 
                    "locked": true, 
                    "nonSpacing": true, 
                    "transform": {
                        "xOffset": 953, 
                        "yOffset": 378
                    }
                }
            ], 
            "flags": 16, 
            "name": "Blk"
        }, 
        {
            "advanceWidth": 1566, 
            "anchors": [
                {
                    "name": "top", 
                    "point": "803 1550"
                }, 
                {
                    "name": "bottom", 
                    "point": "789 -150"
                }
            ], 
            "autoRecipe": "=Y+uni0308.case@top", 
            "color": "#00cce5", 
            "elements": [
                {
                    "component": {
                        "glyphName": "Y"
                    }, 
                    "locked": true
                }, 
                {
                    "component": {
                        "glyphName": "uni0308.case"
                    }, 
                    "locked": true, 
                    "nonSpacing": true, 
                    "transform": {
                        "xOffset": 803, 
                        "yOffset": 400
                    }
                }
            ], 
            "flags": 16, 
            "name": "Medium"
        }, 
        {
            "active": true, 
            "advanceWidth": 1333, 
            "anchors": [
                {
                    "name": "top", 
                    "point": "667 1550"
                }, 
                {
                    "name": "bottom", 
                    "point": "667 -150"
                }
            ], 
            "autoRecipe": "=Y+uni0308.case@top", 
            "color": "#bac000", 
            "elements": [
                {
                    "component": {
                        "glyphName": "Y"
                    }, 
                    "locked": true
                }, 
                {
                    "component": {
                        "glyphName": "uni0308.case"
                    }, 
                    "locked": true, 
                    "nonSpacing": true, 
                    "transform": {
                        "xOffset": 667, 
                        "yOffset": 400
                    }
                }
            ], 
            "flags": 16, 
            "name": "Lt"
        }
    ], 
    "name": "Ydieresis", 
    "unicode": "0178"
}